{
  "/_app": "pages/_app.js",
  "/_document": "pages/_document.js",
  "/_error": "pages/_error.js",
  "/animalRace": "pages/animalRace.html",
  "/": "pages/index.html",
  "/gameCenter": "pages/gameCenter.html",
  "/miniStore": "pages/miniStore.html",
  "/simpleCalculator": "pages/simpleCalculator.html",
  "/website1": "pages/website1.html",
  "/website2": "pages/website2.html",
  "/ultimateChat": "pages/ultimateChat.html",
  "/website3": "pages/website3.html",
  "/studentStore": "pages/studentStore.html",
  "/404": "pages/404.html"
}